<xml>
<EQUATIONS_OF_STATE>
<EQUATION_TYPE>
Birch 1st order
</EQUATION_TYPE>
<CHI_SQUARE>
       9.341853497842E-09
</CHI_SQUARE>
</EQUATIONS_OF_STATE>
<EQUATIONS_PARAMETERS>
<EQUILIBRIUM_VOLUME_AU_A>
    1.739326444043757E+02    2.577415872665270E+01
</EQUILIBRIUM_VOLUME_AU_A>
<BULK_MODULUS_KBAR>
    1.913261483038022E+03
</BULK_MODULUS_KBAR>
<DERIVATIVE_BULK_MODULUS>
    4.135584823134851E+00
</DERIVATIVE_BULK_MODULUS>
<SECOND_DERIVATIVE_BULK_MODULUS>
    0.000000000000000E+00
</SECOND_DERIVATIVE_BULK_MODULUS>
<MINIMUM_ENERGY_RY>
   -4.485869063265392E+02
</MINIMUM_ENERGY_RY>
<CELL_FACTOR>
    0.000000000000000E+00
</CELL_FACTOR>
</EQUATIONS_PARAMETERS>
<FIT_CHECK>
<NUMBER_OF_DATA>
      21
</NUMBER_OF_DATA>
<VOL_ENE_EFIT_DELTA_P_GIBBS>
    1.738408000000000E+02   -4.485869376200000E+02   -4.485869060108689E+02   -3.160913109923058E-05    1.011660867176841E+00   -4.485857420940787E+02
    1.764484000000000E+02   -4.485866878000000E+02   -4.485866754428085E+02   -1.235719145142866E-05   -2.667147651322205E+01   -4.486186794851610E+02
    1.817415000000000E+02   -4.485847778600000E+02   -4.485847917038577E+02    1.384385774372277E-05   -7.673660430323886E+01   -4.486795823746696E+02
    1.871394000000000E+02   -4.485811282600000E+02   -4.485811540157883E+02    2.575578832875181E-05   -1.203835328087783E+02   -4.487342739048146E+02
    1.926431000000000E+02   -4.485758905500000E+02   -4.485759213906197E+02    3.084061972913332E-05   -1.583157186107463E+02   -4.487832146691024E+02
    1.982537000000000E+02   -4.485692050600000E+02   -4.485692396279051E+02    3.456790511791041E-05   -1.911600784767096E+02   -4.488268317391141E+02
    2.039723000000000E+02   -4.485612052600000E+02   -4.485612424896952E+02    3.722969518094033E-05   -2.194748919168875E+02   -4.488655237713547E+02
    2.097997000000000E+02   -4.485520188200000E+02   -4.485520532440193E+02    3.442401930442429E-05   -2.437564943736706E+02   -4.488996617424617E+02
    2.157371000000000E+02   -4.485417668500000E+02   -4.485417845649710E+02    1.771497096569874E-05   -2.644493428330963E+02   -4.489295952982644E+02
    2.279458000000000E+02   -4.485185077800000E+02   -4.485184158658917E+02   -9.191410828179869E-05   -2.966090379450565E+02   -4.489781165517638E+02
    1.687030000000000E+02   -4.485859049600000E+02   -4.485858289606273E+02   -7.599937271152157E-05    6.221696575356689E+01   -4.485145533188344E+02
    1.661725000000000E+02   -4.485845679000000E+02   -4.485844720016736E+02   -9.589832637857398E-05    9.597524886355085E+01   -4.484761525603919E+02
    1.611876000000000E+02   -4.485801097800000E+02   -4.485799893897662E+02   -1.203902337465479E-04    1.704481511431219E+02   -4.483933444508177E+02
    1.563035000000000E+02   -4.485730779700000E+02   -4.485729589943787E+02   -1.189756213193505E-04    2.551465351986236E+02   -4.483019772243576E+02
    1.515190000000000E+02   -4.485632223800000E+02   -4.485631345502279E+02   -8.782977215560095E-05    3.513444372663716E+02   -4.482013357725539E+02
    1.468332000000000E+02   -4.485502722400000E+02   -4.485502474073034E+02   -2.483269662434395E-05    4.604734725302676E+02   -4.480906498110251E+02
    1.422450000000000E+02   -4.485339306400000E+02   -4.485340033547493E+02    7.271474930803379E-05    5.841545596529867E+02   -4.479690754616816E+02
    1.377534000000000E+02   -4.485139409400000E+02   -4.485140807336343E+02    1.397936343323636E-04    7.242172931879674E+02   -4.478357631673188E+02
    1.333574000000000E+02   -4.484899451600000E+02   -4.484901274623586E+02    1.823023586098316E-04    8.827310751501265E+02   -4.476897095576979E+02
    1.248478000000000E+02   -4.484286953900000E+02   -4.484285460600299E+02   -1.493299700427997E-04    1.264816114195175E+03   -4.473552483622654E+02
    1.737894500000000E+02   -4.485866856100000E+02   -4.485869055588243E+02    2.199488242808911E-04    1.578475158858139E+00   -4.485848208047021E+02
</VOL_ENE_EFIT_DELTA_P_GIBBS>
</FIT_CHECK>
